KWD.cpython-39-x86_64-linux-gnu.so
Spatial_KWD-0.4.0.dist-info/LICENSE
Spatial_KWD-0.4.0.dist-info/METADATA
Spatial_KWD-0.4.0.dist-info/WHEEL
Spatial_KWD-0.4.0.dist-info/top_level.txt
Spatial_KWD-0.4.0.dist-info/RECORD
Spatial_KWD.libs/libgomp-f7e03b3e.so.1.0.0
