Metadata-Version: 2.1
Name: Spatial-KWD
Version: 0.4.0
Summary: Spatial KWD for Large Spatial Maps
Home-page: https://github.com/eurostat/Spatial-KWD
Author: Stefano Gualandi
Author-email: stefano.gualandi@gmail.com
License: UNKNOWN
Download-URL: https://github.com/eurostat/Spatial-KWD/archive/v0.4.0-alpha.tar.gz
Platform: linux
Platform: macosx
Platform: windows
Requires-Dist: numpy
